alarmageddon/__init__.py
alarmageddon/banner.py
alarmageddon/config.py
alarmageddon/reporter.py
alarmageddon/result.py
alarmageddon/run.py
alarmageddon/publishing/__init__.py
alarmageddon/publishing/emailer.py
alarmageddon/publishing/exceptions.py
alarmageddon/publishing/graphite.py
alarmageddon/publishing/hipchat.py
alarmageddon/publishing/http.py
alarmageddon/publishing/junit.py
alarmageddon/publishing/pagerduty.py
alarmageddon/publishing/publisher.py
alarmageddon/publishing/slack.py
alarmageddon/publishing/teams.py
alarmageddon/validations/__init__.py
alarmageddon/validations/cassandra.py
alarmageddon/validations/exceptions.py
alarmageddon/validations/graphite.py
alarmageddon/validations/graphite_expectations.py
alarmageddon/validations/http.py
alarmageddon/validations/http_expectations.py
alarmageddon/validations/json_expectations.py
alarmageddon/validations/kafka.py
alarmageddon/validations/rabbitmq.py
alarmageddon/validations/ssh.py
alarmageddon/validations/utilities.py
alarmageddon/validations/validation.py
Alarmageddon-1.1.2.dist-info/LICENSE
Alarmageddon-1.1.2.dist-info/METADATA
Alarmageddon-1.1.2.dist-info/WHEEL
Alarmageddon-1.1.2.dist-info/top_level.txt
Alarmageddon-1.1.2.dist-info/RECORD
